genepy3d_gpl/__init__.py
genepy3d_gpl/interact/__init__.py
genepy3d_gpl/interact/curvesurface.py
genepy3d_gpl/interact/pointsurface.py
genepy3d_gpl/obj/__init__.py
genepy3d_gpl/obj/curves.py
genepy3d_gpl/obj/points.py
genepy3d_gpl/obj/surfaces.py
genepy3d_gpl/util/__init__.py
genepy3d_gpl/util/mayavi.py
genepy3d_gpl-0.3.1.dist-info/LICENSE
genepy3d_gpl-0.3.1.dist-info/METADATA
genepy3d_gpl-0.3.1.dist-info/WHEEL
genepy3d_gpl-0.3.1.dist-info/top_level.txt
genepy3d_gpl-0.3.1.dist-info/RECORD
