Metadata-Version: 2.1
Name: genepy3d_gpl
Version: 0.3.1
Summary: GeNePy3D functions under GPL-like license
Home-page: https://gitlab.com/genepy3d/genepy3d_gpl
Author: genepy3d-team
License: GPL
Classifier: License :: OSI Approved :: GNU General Public License v3 (GPLv3)
Classifier: Programming Language :: Python :: 3
Classifier: Programming Language :: Python :: 3.9
Requires-Python: >=3.9
License-File: LICENSE
Requires-Dist: genepy3d>=0.3.1
